dlc2action/__init__.py
dlc2action/options.py
dlc2action/utils.py
dlc2action/version.py
dlc2action/config/general.yaml
dlc2action/config/losses.yaml
dlc2action/config/metrics.yaml
dlc2action/config/ssl.yaml
dlc2action/config/training.yaml
dlc2action/config/annotation/boris.yaml
dlc2action/config/annotation/calms21.yaml
dlc2action/config/annotation/csv.yaml
dlc2action/config/annotation/dlc.yaml
dlc2action/config/annotation/simba.yaml
dlc2action/config/augmentations/heatmap.yaml
dlc2action/config/augmentations/kinematic.yaml
dlc2action/config/data/calms21.yaml
dlc2action/config/data/dlc_track.yaml
dlc2action/config/data/dlc_tracklet.yaml
dlc2action/config/data/features.yaml
dlc2action/config/data/np_3d.yaml
dlc2action/config/data/simba.yaml
dlc2action/config/features/heatmap.yaml
dlc2action/config/features/kinematic.yaml
dlc2action/config/model/asformer.yaml
dlc2action/config/model/c2f_tcn.yaml
dlc2action/config/model/c2f_transformer.yaml
dlc2action/config/model/edtcn.yaml
dlc2action/config/model/mlp.yaml
dlc2action/config/model/motionbert.yaml
dlc2action/config/model/ms_tcn3.yaml
dlc2action/config/model/transformer.yaml
dlc2action/data/__init__.py
dlc2action/data/annotation_store.py
dlc2action/data/base_store.py
dlc2action/data/dataset.py
dlc2action/data/input_store.py
dlc2action/feature_extraction/__init__.py
dlc2action/loss/__init__.py
dlc2action/loss/asymmetric_loss.py
dlc2action/loss/contrastive.py
dlc2action/loss/contrastive_frame.py
dlc2action/loss/ms_tcn.py
dlc2action/loss/mse.py
dlc2action/loss/tcc.py
dlc2action/metric/__init__.py
dlc2action/metric/base_metric.py
dlc2action/metric/metrics.py
dlc2action/model/__init__.py
dlc2action/model/asformer.py
dlc2action/model/base_model.py
dlc2action/model/c2f_tcn.py
dlc2action/model/c2f_tcn_par.py
dlc2action/model/c2f_transformer.py
dlc2action/model/c3d.py
dlc2action/model/edtcn.py
dlc2action/model/mlp.py
dlc2action/model/motionbert.py
dlc2action/model/motionbert_modules.py
dlc2action/model/ms_tcn.py
dlc2action-1.0.dist-info/licenses/LICENSE.yml
dlc2action-1.0.dist-info/licenses/NOTICE.yml
dlc2action-1.0.dist-info/METADATA
dlc2action-1.0.dist-info/WHEEL
dlc2action-1.0.dist-info/entry_points.txt
dlc2action-1.0.dist-info/top_level.txt
dlc2action-1.0.dist-info/RECORD
