Metadata-Version: 2.4
Name: dlc2action
Version: 1.0
Summary: DLC2Action is a deep learning based action segmentation toolbox. It is designed to work directly on top of markerless pose estimation softwares such as DeepLabCut. It allows to train and evaluate various state-of-the-art action segmentation models on your own data.
Home-page: https://github.com/amathislab/DLC2Action
Author: A. Mathis Lab
Author-email: alexander@deeplabcut.org
Classifier: Programming Language :: Python :: 3
Classifier: License :: OSI Approved :: GNU Lesser General Public License v3 (LGPLv3)
Classifier: Operating System :: OS Independent
Requires-Python: >=3.10
License-File: LICENSE.yml
License-File: NOTICE.yml
Requires-Dist: tqdm
Requires-Dist: torch
Requires-Dist: numpy
Requires-Dist: scipy
Requires-Dist: pandas
Requires-Dist: matplotlib
Requires-Dist: editdistance
Requires-Dist: optuna
Requires-Dist: openpyxl
Requires-Dist: plotly
Requires-Dist: ruamel.yaml
Requires-Dist: p_tqdm
Requires-Dist: click
Requires-Dist: pyinquirer
Requires-Dist: pytest
Requires-Dist: tables
Requires-Dist: torchvision
Requires-Dist: tika
Requires-Dist: pdfplumber
Requires-Dist: ftfy
Requires-Dist: regex
Requires-Dist: scikit-learn
Requires-Dist: einops
Requires-Dist: ipykernel
Requires-Dist: opencv-python
Requires-Dist: seaborn
Requires-Dist: pillow
Dynamic: author
Dynamic: author-email
Dynamic: classifier
Dynamic: description
Dynamic: description-content-type
Dynamic: home-page
Dynamic: license-file
Dynamic: requires-dist
Dynamic: requires-python
Dynamic: summary
